{
	"clientwh_request_title": "Phiếu yêu cầu",
	"clientwh_request_idstore": "Kho",
	"clientwh_requestdetail_title": "Chi tiết phiếu yêu cầu",
	"clientwh_request_idwriter": "Người lập phiếu",
	"clientwh_request_idreceiver": "Người nhận",
	"clientwh_request_idresponsible": "Người chịu trách nhiệm",
	"clientwh_request_code": "Mã Phiếu",
	"clientwh_request_name": "Tên Phiếu",
	"clientwh_request_receiverphonenumber": "Số điện thoại người nhận phiếu",
	"clientwh_request_writerphonenumber": "Số điện thoại người lập phiếu",
	"clientwh_request_address": "Địa chỉ",
	"clientwh_request_times": "Số lần",
	"clientwh_request_requestdate": "Ngày yêu cầu",
	"clientwh_request_receivedate": "Ngày nhận",
	"clientwh_request_note": "Ghi chú",
	"clientwh_request_status": "status",
	"clientwh_request_idowner": "idowner",
	"clientwh_request_idcreate": "idcreate",
	"clientwh_request_idupdate": "idupdate",
	"clientwh_request_iddelete": "iddelete",
	"clientwh_request_idlock": "idlock",
	"clientwh_request_createdate": "createdate",
	"clientwh_request_updatedate": "updatedate",
	"clientwh_request_deletedate": "deletedate",
	"clientwh_request_lockdate": "lockdate",
	"clientwh_request_version": "Phiên bản",
	"clientwh_request_send": "Gửi",
	"clientwh_request_receiver": "Gửi tới người nhận",
	"clientwh_request_approver": "Gửi tới người duyệt",
	"clientwh_request_duration": "Thời hạn",
	"clientwh_request_search": "Tìm",
	"clientwh_request_store": "Kho",
	"clientwh_request_choose":"Chọn kho",
	"clientwh_request_store_exist": "Chọn kho đã tồn tại",
	"clientwh_request_writer_exist": "Chọn người viết đơn đã tồn tại",
	"clientwh_request_receiver_exist": "Chọn người nhận đã tồn tại",
	"clientwh_request_responsible_exist": "Chọn người chịu trách nhiệm đã tồn tại",
	"clientwh_created_request_title": "Phiếu yêu cầu chưa gửi",
	"clientwh_received_request_title": "Phiếu yêu cầu được gửi tới",
	"clientwh_sent_request_title": "Phiếu yêu cầu đã gửi",
	"clientwh_assigned_request_title": "Phiếu yêu cầu chờ duyệt",
	"clientwh_request_sign": "Duyệt",
	"clientwh_request_attachment_title": "Tệp đính kèm",
	"clientwh_quotation_date": "Ngày yêu cầu phải nhỏ hơn ngày nhận, vui lòng kiểm tra lại dữ liệu!"
}
